iota_wallet-1.0.0rc2.dist-info/METADATA
iota_wallet-1.0.0rc2.dist-info/WHEEL
iota_wallet/account.py
iota_wallet/common.py
iota_wallet/secret_manager.py
iota_wallet/wallet.py
iota_wallet/__init__.py
iota_wallet/iota_wallet.cp310-win_amd64.pyd
iota_wallet-1.0.0rc2.dist-info/RECORD
